AUTHORS.md
LICENSE.md
README.md
setup.py
ttkwidgets/__init__.py
ttkwidgets/autohidescrollbar.py
ttkwidgets/calendarwidget.py
ttkwidgets/checkboxtreeview.py
ttkwidgets/debugwindow.py
ttkwidgets/hook.py
ttkwidgets/itemscanvas.py
ttkwidgets/linklabel.py
ttkwidgets/scaleentry.py
ttkwidgets/scrolledlistbox.py
ttkwidgets/table.py
ttkwidgets/tickscale.py
ttkwidgets/timeline.py
ttkwidgets/tooltips.py
ttkwidgets/utilities.py
ttkwidgets.egg-info/PKG-INFO
ttkwidgets.egg-info/SOURCES.txt
ttkwidgets.egg-info/dependency_links.txt
ttkwidgets.egg-info/requires.txt
ttkwidgets.egg-info/top_level.txt
ttkwidgets/assets/balloon.png
ttkwidgets/assets/checked.png
ttkwidgets/assets/closed.png
ttkwidgets/assets/drag.png
ttkwidgets/assets/marker.png
ttkwidgets/assets/open.png
ttkwidgets/assets/tristate.png
ttkwidgets/assets/unchecked.png
ttkwidgets/assets/zoom_in.png
ttkwidgets/assets/zoom_out.png
ttkwidgets/assets/zoom_reset.png
ttkwidgets/autocomplete/__init__.py
ttkwidgets/autocomplete/autocomplete_entry.py
ttkwidgets/autocomplete/autocomplete_entrylistbox.py
ttkwidgets/autocomplete/autocompletecombobox.py
ttkwidgets/color/__init__.py
ttkwidgets/color/alphabar.py
ttkwidgets/color/colorpicker.py
ttkwidgets/color/colorsquare.py
ttkwidgets/color/functions.py
ttkwidgets/color/gradientbar.py
ttkwidgets/color/limitvar.py
ttkwidgets/color/spinbox.py
ttkwidgets/font/__init__.py
ttkwidgets/font/chooser.py
ttkwidgets/font/familydropdown.py
ttkwidgets/font/familylistbox.py
ttkwidgets/font/propertiesframe.py
ttkwidgets/font/selectframe.py
ttkwidgets/font/sizedropdown.py
ttkwidgets/frames/__init__.py
ttkwidgets/frames/scrolledframe.py
ttkwidgets/frames/toggledframe.py
ttkwidgets/frames/tooltip.py
ttkwidgets/validated_entries/__init__.py
ttkwidgets/validated_entries/numbers.py
ttkwidgets/validated_entries/strings.py
ttkwidgets/validated_entries/validated_entry.py
ttkwidgets/validated_entries/validators.py