Metadata-Version: 2.1
Name: ttkwidgets
Version: 0.13.0
Summary:  A collection of widgets for Tkinter's ttk extensions by various authors 
Home-page: https://www.github.com/RedFantom/ttkwidgets
Author: The ttkwidgets authors
License: AGPL
Download-URL: https://www.github.com/RedFantom/ttkwidgets/releases
Platform: UNKNOWN
Classifier: Programming Language :: Python :: 3
Classifier: License :: OSI Approved :: GNU General Public License v3 (GPLv3)
Requires-Python: >=3.6
License-File: LICENSE.md
License-File: AUTHORS.md
